README.rst
setup.py
minitrue/__init__.py
minitrue/misdirection.py
minitrue/proxy.py
minitrue/utils.py
minitrue.egg-info/PKG-INFO
minitrue.egg-info/SOURCES.txt
minitrue.egg-info/dependency_links.txt
minitrue.egg-info/requires.txt
minitrue.egg-info/top_level.txt
minitrue/test/__init__.py
minitrue/test/connect.py
minitrue/test/observer.py
minitrue/test/test_functional.py