Metadata-Version: 1.1
Name: minitrue
Version: 20130126
Summary: Proxy designed to lie.
Home-page: https://github.com/lvh/minitrue
Author: Laurens Van Houtven
Author-email: _@lvh.cc
License: ISC
Platform: UNKNOWN
Classifier: Development Status :: 3 - Alpha
Classifier: Framework :: Twisted
Classifier: License :: OSI Approved :: ISC License (ISCL)
Classifier: Topic :: Internet :: Proxy Servers
Classifier: Topic :: Internet :: WWW/HTTP
Classifier: Topic :: Security
